setup.py
pyAirlock/__init__.py
pyAirlock/common/config.py
pyAirlock/common/exception.py
pyAirlock/common/log.py
pyAirlock/common/lookup.py
pyAirlock/common/output.py
pyAirlock/common/utils.py
pyAirlock/gateway/__init__ copy.py
pyAirlock/gateway/__init__.py
pyAirlock/gateway/config_api/__init__.py
pyAirlock/gateway/config_api/anomalyshield_application.py
pyAirlock/gateway/config_api/anomalyshield_rule.py
pyAirlock/gateway/config_api/anomalyshield_settings.py
pyAirlock/gateway/config_api/anomalyshield_trafficmatcher.py
pyAirlock/gateway/config_api/anomalyshield_trigger.py
pyAirlock/gateway/config_api/api_policy.py
pyAirlock/gateway/config_api/backendgroup.py
pyAirlock/gateway/config_api/certificate.py
pyAirlock/gateway/config_api/configuration.py
pyAirlock/gateway/config_api/element.py
pyAirlock/gateway/config_api/gateway.py
pyAirlock/gateway/config_api/graphql.py
pyAirlock/gateway/config_api/host.py
pyAirlock/gateway/config_api/icap.py
pyAirlock/gateway/config_api/iplist.py
pyAirlock/gateway/config_api/jwks.py
pyAirlock/gateway/config_api/kerberos.py
pyAirlock/gateway/config_api/license.py
pyAirlock/gateway/config_api/log_settings.py
pyAirlock/gateway/config_api/mapping.py
pyAirlock/gateway/config_api/network_endpoint.py
pyAirlock/gateway/config_api/network_services_settings.py
pyAirlock/gateway/config_api/node.py
pyAirlock/gateway/config_api/openapi.py
pyAirlock/gateway/config_api/reporting_settings.py
pyAirlock/gateway/config_api/route.py
pyAirlock/gateway/config_api/route_settings.py
pyAirlock/gateway/config_api/session_settings.py
pyAirlock/gateway/config_api/vhost.py
pyAirlock/iam/adminapp/__init__.py
samples/config.yaml
pyAirlock-1.0.1.dist-info/COPYING
pyAirlock-1.0.1.dist-info/METADATA
pyAirlock-1.0.1.dist-info/WHEEL
pyAirlock-1.0.1.dist-info/top_level.txt
pyAirlock-1.0.1.dist-info/RECORD
