Metadata-Version: 2.1
Name: pyAirlock
Version: 1.0.1
Summary: Python library for Airlock product REST APIs
Author-email: Urs Zurbuchen <info@airlock.com>
Project-URL: Official Website, https://www.airlock.com
Project-URL: Homepage, https://github.com/alalazu/pyAirlock
Keywords: airlock
Classifier: License :: OSI Approved :: GNU General Public License v3 (GPLv3)
Classifier: Development Status :: 4 - Beta
Classifier: Programming Language :: Python
Classifier: Programming Language :: Python :: 3
Classifier: Intended Audience :: Developers
Classifier: Intended Audience :: Information Technology
Classifier: Intended Audience :: System Administrators
Classifier: Topic :: Software Development :: Libraries :: Python Modules
Requires-Python: >=3.11
License-File: COPYING
Requires-Dist: pyyaml
Requires-Dist: colorama
Requires-Dist: requests
Requires-Dist: pdoc3
